odoo/addons/cooperator_worker_force/README.rst
odoo/addons/cooperator_worker_force/__init__.py
odoo/addons/cooperator_worker_force/__manifest__.py
odoo/addons/cooperator_worker_force/i18n/cooperator_worker_force.pot
odoo/addons/cooperator_worker_force/models/__init__.py
odoo/addons/cooperator_worker_force/models/res_partner.py
odoo/addons/cooperator_worker_force/readme/CONTRIBUTORS.rst
odoo/addons/cooperator_worker_force/readme/CREDITS.rst
odoo/addons/cooperator_worker_force/readme/DESCRIPTION.rst
odoo/addons/cooperator_worker_force/static/description/index.html
odoo/addons/cooperator_worker_force/tests/__init__.py
odoo/addons/cooperator_worker_force/tests/test_worker_store.py
odoo/addons/cooperator_worker_force/views/res_partner.xml
odoo12_addon_cooperator_worker_force-12.0.2.0.1.99.dev1.dist-info/METADATA
odoo12_addon_cooperator_worker_force-12.0.2.0.1.99.dev1.dist-info/WHEEL
odoo12_addon_cooperator_worker_force-12.0.2.0.1.99.dev1.dist-info/top_level.txt
odoo12_addon_cooperator_worker_force-12.0.2.0.1.99.dev1.dist-info/RECORD
