Metadata-Version: 2.1
Name: odoo12-addon-cooperator-worker-force
Version: 12.0.2.0.1.99.dev1
Summary: Allows to set a cooperator as a worker before the share is released.
Home-page: https://github.com/beescoop/Obeesdoo
Author: Poll'n Coop, Coop IT Easy SC
License: AGPL-3
Platform: UNKNOWN
Classifier: Programming Language :: Python
Classifier: Framework :: Odoo
Classifier: Framework :: Odoo :: 12.0
Classifier: License :: OSI Approved :: GNU Affero General Public License v3
Requires-Python: >=3.5
Requires-Dist: odoo12-addon-cooperator-worker
Requires-Dist: odoo (<12.1dev,>=12.0a)
